KamuJpModern/ModernLogging.py
KamuJpModern/ModernProgressBar.py
KamuJpModern/__init__.py
KamuJpModern/__main__.py
kamu_jp_modern-10.0.3.dist-info/METADATA
kamu_jp_modern-10.0.3.dist-info/WHEEL
kamu_jp_modern-10.0.3.dist-info/top_level.txt
kamu_jp_modern-10.0.3.dist-info/RECORD
