Metadata-Version: 2.1
Name: kamu-jp-modern
Version: 10.0.3
Summary: Modern is a simple package for logging and progress bar and More!
Home-page: https://github.com/DiamondGotCat/Modern
Author: DiamondGotCat
Author-email: chii@kamu.jp
Classifier: Programming Language :: Python :: 3
Classifier: License :: OSI Approved :: MIT License
Classifier: Operating System :: OS Independent
Requires-Python: >=3.6
